{
 "items": [
  {
   "snippet": {
    "publishedAt": "2012-02-16T14:59:23.000Z",
    "title": "Joan Soriano: NPR Music Tiny Desk Concert",
    "description": "With his songs of heartache, Soriano is an essential piece of the \nbachata story. Known as \"El Duque de la Bachata\" (\"The Duke of \nBachata\"), Soriano gives a raw but beautiful performance at the NPR \nMusic offices.\n\nSet List:\n\n\"Me Decidí A Dejarte\"\n\"Aunque Sea A Escondidas\"\n\"Cuanto Lloré\"\n\nFor more videos and to subscribe to the Tiny Desk Concerts podcast, visit npr.org/tinydeskconcerts.",
    "thumbnails": {
     "default": {
      "url": "https://i.ytimg.com/vi/XnCyyJhJCc0/default.jpg",
      "width": 120,
      "height": 90
     },
     "medium": {
      "url": "https://i.ytimg.com/vi/XnCyyJhJCc0/mqdefault.jpg",
      "width": 320,
      "height": 180
     },
     "high": {
      "url": "https://i.ytimg.com/vi/XnCyyJhJCc0/hqdefault.jpg",
      "width": 480,
      "height": 360
     },
     "standard": {
      "url": "https://i.ytimg.com/vi/XnCyyJhJCc0/sddefault.jpg",
      "width": 640,
      "height": 480
     },
     "maxres": {
      "url": "https://i.ytimg.com/vi/XnCyyJhJCc0/maxresdefault.jpg",
      "width": 1280,
      "height": 720
     }
    },
    "position": 400
   }
  },
  {
   "snippet": {
    "publishedAt": "2012-02-14T15:21:32.000Z",
    "title": "Red Baraat: NPR Music Tiny Desk Concert",
    "description": "One of the best party bands around, Red Baarat plays rollicking funk music steeped in Northern India's wedding celebrations, with a dash of D.C. go-go beats and hip-hop. The dance-friendly group performs a loud, high-energy set at the NPR Music offices.\n\nSet List: \n\n\"Chaal Baby\"\n\"Shruggy Ji\"\n\"Dhol 'n' Brass\"\n\nFor more videos and to subscribe to the Tiny Desk Concerts podcast, visit npr.org/tinydeskconcerts.",
    "thumbnails": {
     "default": {
      "url": "https://i.ytimg.com/vi/0kQD1P0_KUs/default.jpg",
      "width": 120,
      "height": 90
     },
     "medium": {
      "url": "https://i.ytimg.com/vi/0kQD1P0_KUs/mqdefault.jpg",
      "width": 320,
      "height": 180
     },
     "high": {
      "url": "https://i.ytimg.com/vi/0kQD1P0_KUs/hqdefault.jpg",
      "width": 480,
      "height": 360
     },
     "standard": {
      "url": "https://i.ytimg.com/vi/0kQD1P0_KUs/sddefault.jpg",
      "width": 640,
      "height": 480
     },
     "maxres": {
      "url": "https://i.ytimg.com/vi/0kQD1P0_KUs/maxresdefault.jpg",
      "width": 1280,
      "height": 720
     }
    },
    "position": 401
   }
  },
  {
   "snippet": {
    "publishedAt": "2012-02-14T15:03:37.000Z",
    "title": "Craig Finn: NPR Music Tiny Desk Concert",
    "description": "All these mournful, inward-facing songs (including the unreleased \"Jeremiah's Blues\") require is the Hold Steady singer, his acoustic guitar and the indispensable pedal steel of Ricky Ray Jackson.\n\nSet List:\n\n\"Apollo Bay\"\n\"Western Pier\"\n\"Jeremiah's Blues\"\n\nFor more videos and to subscribe to the Tiny Desk Concerts podcast, visit npr.org/tinydeskconcerts.",
    "thumbnails": {
     "default": {
      "url": "https://i.ytimg.com/vi/J8QBpfCSlLE/default.jpg",
      "width": 120,
      "height": 90
     },
     "medium": {
      "url": "https://i.ytimg.com/vi/J8QBpfCSlLE/mqdefault.jpg",
      "width": 320,
      "height": 180
     },
     "high": {
      "url": "https://i.ytimg.com/vi/J8QBpfCSlLE/hqdefault.jpg",
      "width": 480,
      "height": 360
     },
     "standard": {
      "url": "https://i.ytimg.com/vi/J8QBpfCSlLE/sddefault.jpg",
      "width": 640,
      "height": 480
     },
     "maxres": {
      "url": "https://i.ytimg.com/vi/J8QBpfCSlLE/maxresdefault.jpg",
      "width": 1280,
      "height": 720
     }
    },
    "position": 402
   }
  },
  {
   "snippet": {
    "publishedAt": "2012-02-14T15:03:27.000Z",
    "title": "The Creole Choir Of Cuba: NPR Music Tiny Desk Concert",
    "description": "With a musical history that dates back to the late 18th century, the group has revitalized a long-lost culture through music performed largely a cappella and entirely in Haitian Creole. Watch The Creole Choir of Cuba mash up Cuban and Haitian cultures in this spirited set at the NPR Music offices.\n\nSet List:\n\n\"Marasa Elu\"\n\"Ayiti Krye\"\n\"Lumane Casimir\"\n\nFor more videos and to subscribe to the Tiny Desk Concerts podcast, visit npr.org/tinydeskconcerts.",
    "thumbnails": {
     "default": {
      "url": "https://i.ytimg.com/vi/pJSv2hoH5ro/default.jpg",
      "width": 120,
      "height": 90
     },
     "medium": {
      "url": "https://i.ytimg.com/vi/pJSv2hoH5ro/mqdefault.jpg",
      "width": 320,
      "height": 180
     },
     "high": {
      "url": "https://i.ytimg.com/vi/pJSv2hoH5ro/hqdefault.jpg",
      "width": 480,
      "height": 360
     },
     "standard": {
      "url": "https://i.ytimg.com/vi/pJSv2hoH5ro/sddefault.jpg",
      "width": 640,
      "height": 480
     },
     "maxres": {
      "url": "https://i.ytimg.com/vi/pJSv2hoH5ro/maxresdefault.jpg",
      "width": 1280,
      "height": 720
     }
    },
    "position": 403
   }
  },
  {
   "snippet": {
    "publishedAt": "2012-02-04T23:50:30.000Z",
    "title": "Bill Frisell: NPR Music Tiny Desk Concert",
    "description": "The brilliant and nimble guitarist reinvents the songs of John Lennon at the NPR Music offices.\n\nSet List:\n\n\nNowhere Man\"\n\"In My Life\"\n\"Strawberry Fields Forever\"\n\nFor more videos and to subscribe to the Tiny Desk Concerts podcast, visit npr.org/tinydeskconcerts.",
    "thumbnails": {
     "default": {
      "url": "https://i.ytimg.com/vi/NO-1Euq2RBk/default.jpg",
      "width": 120,
      "height": 90
     },
     "medium": {
      "url": "https://i.ytimg.com/vi/NO-1Euq2RBk/mqdefault.jpg",
      "width": 320,
      "height": 180
     },
     "high": {
      "url": "https://i.ytimg.com/vi/NO-1Euq2RBk/hqdefault.jpg",
      "width": 480,
      "height": 360
     },
     "standard": {
      "url": "https://i.ytimg.com/vi/NO-1Euq2RBk/sddefault.jpg",
      "width": 640,
      "height": 480
     },
     "maxres": {
      "url": "https://i.ytimg.com/vi/NO-1Euq2RBk/maxresdefault.jpg",
      "width": 1280,
      "height": 720
     }
    },
    "position": 404
   }
  },
  {
   "snippet": {
    "publishedAt": "2012-02-04T21:10:58.000Z",
    "title": "Girl In A Coma: NPR Music Tiny Desk Concert",
    "description": "Girl In A Coma is known for crunchy guitars, seamless musical interplay and Nina Diaz's alluring voice. But here, the San Antonio trio deftly gets back to basics to explore not just the form of its songs, but also the soul of its lyrics.\n\nSet List:\n\n\"Smart\"\n\"Knocking At Your Door\"\n\"So\"\n\nFor more videos and to subscribe to the Tiny Desk Concerts podcast, visit npr.org/tinydeskconcerts.",
    "thumbnails": {
     "default": {
      "url": "https://i.ytimg.com/vi/je2HSRcRruI/default.jpg",
      "width": 120,
      "height": 90
     },
     "medium": {
      "url": "https://i.ytimg.com/vi/je2HSRcRruI/mqdefault.jpg",
      "width": 320,
      "height": 180
     },
     "high": {
      "url": "https://i.ytimg.com/vi/je2HSRcRruI/hqdefault.jpg",
      "width": 480,
      "height": 360
     },
     "standard": {
      "url": "https://i.ytimg.com/vi/je2HSRcRruI/sddefault.jpg",
      "width": 640,
      "height": 480
     },
     "maxres": {
      "url": "https://i.ytimg.com/vi/je2HSRcRruI/maxresdefault.jpg",
      "width": 1280,
      "height": 720
     }
    },
    "position": 405
   }
  },
  {
   "snippet": {
    "publishedAt": "2012-02-01T21:44:36.000Z",
    "title": "Anna Calvi: NPR Music Tiny Desk Concert",
    "description": "The slow build that takes place in just three short songs performed at the NPR Music offices -- from a guitar instrumental to the final primal cry of \"Jezebel\" -- is nothing short of astonishing. Calvi plays three songs from her self-titled debut in this powerful performance at the NPR Music offices.\n\nSet List:\n\"River To The Sea\"\n\"Surrender\"\n\"Jezebel\"\n\nFor more videos and to subscribe to the Tiny Desk Concerts podcast, visit npr.org/tinydeskconcerts.",
    "thumbnails": {
     "default": {
      "url": "https://i.ytimg.com/vi/EScw2XrUHFY/default.jpg",
      "width": 120,
      "height": 90
     },
     "medium": {
      "url": "https://i.ytimg.com/vi/EScw2XrUHFY/mqdefault.jpg",
      "width": 320,
      "height": 180
     },
     "high": {
      "url": "https://i.ytimg.com/vi/EScw2XrUHFY/hqdefault.jpg",
      "width": 480,
      "height": 360
     },
     "standard": {
      "url": "https://i.ytimg.com/vi/EScw2XrUHFY/sddefault.jpg",
      "width": 640,
      "height": 480
     },
     "maxres": {
      "url": "https://i.ytimg.com/vi/EScw2XrUHFY/maxresdefault.jpg",
      "width": 1280,
      "height": 720
     }
    },
    "position": 406
   }
  },
  {
   "snippet": {
    "publishedAt": "2012-01-23T18:40:10.000Z",
    "title": "Glenn Jones: NPR Music Tiny Desk Concerts",
    "description": "Glenn Jones' most recent album, 'The Wanting,' is a compelling work of American folk music that tells stories without a single word. Watch the masterful guitarist perform a lovely set at the NPR Music offices.\n\nSet List:\n\nTinka Marie\"\n\"The Great Pacific Northwest\"\n\"Of Its Own Kind\"\n\nFor more videos and to subscribe to the Tiny Desk Concerts podcast, visit npr.org/tinydeskconcerts.",
    "thumbnails": {
     "default": {
      "url": "https://i.ytimg.com/vi/uPXk1ElmzGs/default.jpg",
      "width": 120,
      "height": 90
     },
     "medium": {
      "url": "https://i.ytimg.com/vi/uPXk1ElmzGs/mqdefault.jpg",
      "width": 320,
      "height": 180
     },
     "high": {
      "url": "https://i.ytimg.com/vi/uPXk1ElmzGs/hqdefault.jpg",
      "width": 480,
      "height": 360
     },
     "standard": {
      "url": "https://i.ytimg.com/vi/uPXk1ElmzGs/sddefault.jpg",
      "width": 640,
      "height": 480
     },
     "maxres": {
      "url": "https://i.ytimg.com/vi/uPXk1ElmzGs/maxresdefault.jpg",
      "width": 1280,
      "height": 720
     }
    },
    "position": 407
   }
  },
  {
   "snippet": {
    "publishedAt": "2012-01-23T18:23:03.000Z",
    "title": "Jake Schepps' Expedition Quartet: NPR Music Tiny Desk Concert",
    "description": "Banjo master Jake Schepps and friends create an intriguing goulash of Bartok, bluegrass and bebop.\n\nSet List:\nBartók (arr. Flinner): Romanian Folk Dances -- \"Stick Game\"\nBartók (arr. Schepps): For Children (Hungarian Folk Tunes) -- \"Stars, Stars Brightly Shine\"\nBartók / traditional (arr. Schepps): Mikrokosmos No. 78 / \"Cousin Sally Brown\"\n\nFor more videos and to subscribe to the Tiny Desk Concerts podcast, visit npr.org/tinydeskconcerts.",
    "thumbnails": {
     "default": {
      "url": "https://i.ytimg.com/vi/4CP2ur8IJxo/default.jpg",
      "width": 120,
      "height": 90
     },
     "medium": {
      "url": "https://i.ytimg.com/vi/4CP2ur8IJxo/mqdefault.jpg",
      "width": 320,
      "height": 180
     },
     "high": {
      "url": "https://i.ytimg.com/vi/4CP2ur8IJxo/hqdefault.jpg",
      "width": 480,
      "height": 360
     },
     "standard": {
      "url": "https://i.ytimg.com/vi/4CP2ur8IJxo/sddefault.jpg",
      "width": 640,
      "height": 480
     },
     "maxres": {
      "url": "https://i.ytimg.com/vi/4CP2ur8IJxo/maxresdefault.jpg",
      "width": 1280,
      "height": 720
     }
    },
    "position": 408
   }
  },
  {
   "snippet": {
    "publishedAt": "2012-01-23T18:11:08.000Z",
    "title": "Screaming Females: NPR Music Tiny Desk Concert",
    "description": "Don't let the size of the amps at the NPR Music office fool you: Screaming Females' music is louder than bombs. Pared down at the Tiny Desk, the band's keen sense of song stays front and center -- especially in \"It All Means Nothing,\" a new song from Screaming Females' next album.\n\nSet List:\n\"It All Means Nothing\"\n\"Little Anne\"\n\"I Don't Mind It\"\n\nFor more videos and to subscribe to the Tiny Desk Concerts podcast, visit npr.org/tinydeskconcerts.",
    "thumbnails": {
     "default": {
      "url": "https://i.ytimg.com/vi/EPn9rgccqqw/default.jpg",
      "width": 120,
      "height": 90
     },
     "medium": {
      "url": "https://i.ytimg.com/vi/EPn9rgccqqw/mqdefault.jpg",
      "width": 320,
      "height": 180
     },
     "high": {
      "url": "https://i.ytimg.com/vi/EPn9rgccqqw/hqdefault.jpg",
      "width": 480,
      "height": 360
     },
     "standard": {
      "url": "https://i.ytimg.com/vi/EPn9rgccqqw/sddefault.jpg",
      "width": 640,
      "height": 480
     },
     "maxres": {
      "url": "https://i.ytimg.com/vi/EPn9rgccqqw/maxresdefault.jpg",
      "width": 1280,
      "height": 720
     }
    },
    "position": 409
   }
  },
  {
   "snippet": {
    "publishedAt": "2012-01-05T15:10:59.000Z",
    "title": "Tinariwen: NPR Music Tiny Desk Concert",
    "description": "Even in a stripped-down acoustic formation, Tinariwen's trance-inducing desert music doesn't disappoint. Watch the Tuareg musicians adorn their beautiful, flowing robes for a stunning set in the NPR Music offices.\n\nSet List:\n\n\"Adounia\"\n\"Takkest Tamidaret\"\n\"Tenhert\"\n\"Tahlamoyt\"\n\nFor more videos and to subscribe to the Tiny Desk Concerts podcast, visit npr.org/tinydeskconcerts.",
    "thumbnails": {
     "default": {
      "url": "https://i.ytimg.com/vi/IdbBmqOUPlY/default.jpg",
      "width": 120,
      "height": 90
     },
     "medium": {
      "url": "https://i.ytimg.com/vi/IdbBmqOUPlY/mqdefault.jpg",
      "width": 320,
      "height": 180
     },
     "high": {
      "url": "https://i.ytimg.com/vi/IdbBmqOUPlY/hqdefault.jpg",
      "width": 480,
      "height": 360
     },
     "standard": {
      "url": "https://i.ytimg.com/vi/IdbBmqOUPlY/sddefault.jpg",
      "width": 640,
      "height": 480
     },
     "maxres": {
      "url": "https://i.ytimg.com/vi/IdbBmqOUPlY/maxresdefault.jpg",
      "width": 1280,
      "height": 720
     }
    },
    "position": 410
   }
  },
  {
   "snippet": {
    "publishedAt": "2011-12-28T20:45:32.000Z",
    "title": "Maria Volonte: Tiny Desk Concert",
    "description": "Argentine singer Maria Volonte's powerful, refreshing interpretation  of tango is fully capable of transplanting itself into folk, Latin  blues or the traditional music of Peru, Uruguay and Brazil. With its mature sensuality, her music is filled  with a potent brew of nostalgia and melancholy.\n\nSet List:\n\"El Beso Azul\"\n\"Oh Viejo Tren\"\n\"SF Tango\"",
    "thumbnails": {
     "default": {
      "url": "https://i.ytimg.com/vi/hXy9_xjOrb8/default.jpg",
      "width": 120,
      "height": 90
     },
     "medium": {
      "url": "https://i.ytimg.com/vi/hXy9_xjOrb8/mqdefault.jpg",
      "width": 320,
      "height": 180
     },
     "high": {
      "url": "https://i.ytimg.com/vi/hXy9_xjOrb8/hqdefault.jpg",
      "width": 480,
      "height": 360
     },
     "standard": {
      "url": "https://i.ytimg.com/vi/hXy9_xjOrb8/sddefault.jpg",
      "width": 640,
      "height": 480
     },
     "maxres": {
      "url": "https://i.ytimg.com/vi/hXy9_xjOrb8/maxresdefault.jpg",
      "width": 1280,
      "height": 720
     }
    },
    "position": 411
   }
  },
  {
   "snippet": {
    "publishedAt": "2011-12-28T20:17:59.000Z",
    "title": "The MusicTapes: NPR Music Tiny Desk Concert",
    "description": "Somewhere inside Julian Koster lives a 13-year-old boy filled with wonder and imagination. Performing with his band The Music Tapes, the Elephant 6 and Neutral Milk Hotel alumnus plays a holiday set complete with bowed banjos, singing saws and tape machines at the NPR Music offices. \n\nSet List:\n\"The First Noel\"\n\"Freeing Song For Reindeer\"\n\"Jesus Blood\"\n\"Takeshi And Elijah\"\n\"Zat You, Santa Claus?\"\n\nFor more videos and to subscribe to the Tiny Desk Concerts podcast, visit npr.org/tinydeskconcerts.",
    "thumbnails": {
     "default": {
      "url": "https://i.ytimg.com/vi/h7PsGipAraQ/default.jpg",
      "width": 120,
      "height": 90
     },
     "medium": {
      "url": "https://i.ytimg.com/vi/h7PsGipAraQ/mqdefault.jpg",
      "width": 320,
      "height": 180
     },
     "high": {
      "url": "https://i.ytimg.com/vi/h7PsGipAraQ/hqdefault.jpg",
      "width": 480,
      "height": 360
     },
     "standard": {
      "url": "https://i.ytimg.com/vi/h7PsGipAraQ/sddefault.jpg",
      "width": 640,
      "height": 480
     },
     "maxres": {
      "url": "https://i.ytimg.com/vi/h7PsGipAraQ/maxresdefault.jpg",
      "width": 1280,
      "height": 720
     }
    },
    "position": 412
   }
  },
  {
   "snippet": {
    "publishedAt": "2011-12-28T20:08:31.000Z",
    "title": "Gem Club: NPR Music Tiny Desk Concert",
    "description": "Maybe you couldn't hear a pin drop when Gem Club played, but you could hear the click of a keyboard. The band stopped by the NPR Music offices to play songs from 2011's 'Breakers.'\n\nSet List:\n\"Animals\"\n\"Breakers\"\n\"252\"\n\nFor more videos and to subscribe to the Tiny Desk Concerts podcast, visit npr.org/tinydeskconcerts.",
    "thumbnails": {
     "default": {
      "url": "https://i.ytimg.com/vi/0HK1KhJgUs4/default.jpg",
      "width": 120,
      "height": 90
     },
     "medium": {
      "url": "https://i.ytimg.com/vi/0HK1KhJgUs4/mqdefault.jpg",
      "width": 320,
      "height": 180
     },
     "high": {
      "url": "https://i.ytimg.com/vi/0HK1KhJgUs4/hqdefault.jpg",
      "width": 480,
      "height": 360
     },
     "standard": {
      "url": "https://i.ytimg.com/vi/0HK1KhJgUs4/sddefault.jpg",
      "width": 640,
      "height": 480
     },
     "maxres": {
      "url": "https://i.ytimg.com/vi/0HK1KhJgUs4/maxresdefault.jpg",
      "width": 1280,
      "height": 720
     }
    },
    "position": 413
   }
  },
  {
   "snippet": {
    "publishedAt": "2011-12-14T19:27:41.000Z",
    "title": "I Wayne: NPR Music Tiny Desk Concert",
    "description": "The reggae star said little between his van and the NPR Music offices. But as soon as the cameras started rolling, he came to life right on cue, showcasing his smooth voice and vibrant energy.\n\nSet List:\n\n\"Real And Clean\"\n\"Can't Satisfy Her\"\n\nFor more videos and to subscribe to the Tiny Desk Concerts podcast visit npr.org/tinydeskconcerts.",
    "thumbnails": {
     "default": {
      "url": "https://i.ytimg.com/vi/jaaQSxUOwC0/default.jpg",
      "width": 120,
      "height": 90
     },
     "medium": {
      "url": "https://i.ytimg.com/vi/jaaQSxUOwC0/mqdefault.jpg",
      "width": 320,
      "height": 180
     },
     "high": {
      "url": "https://i.ytimg.com/vi/jaaQSxUOwC0/hqdefault.jpg",
      "width": 480,
      "height": 360
     },
     "standard": {
      "url": "https://i.ytimg.com/vi/jaaQSxUOwC0/sddefault.jpg",
      "width": 640,
      "height": 480
     },
     "maxres": {
      "url": "https://i.ytimg.com/vi/jaaQSxUOwC0/maxresdefault.jpg",
      "width": 1280,
      "height": 720
     }
    },
    "position": 414
   }
  },
  {
   "snippet": {
    "publishedAt": "2011-12-14T19:19:38.000Z",
    "title": "JEFF The Brotherhood: NPR Music Tiny Desk Concert",
    "description": "Like the Ramones or early Weezer, the Nashville power-punk duo JEFF The Brotherhood is really good at being funny without writing gimmicky songs. And, while \"Bummer\" ostensibly comes off a breakup record, We Are the Champions, it functions in the same humorously harsh way as Weezer's Pinkerton. You really feel for these guys, but you still want to bum-rush the mic and sing along, especially during the fuzzy rager \"Shredder.\" And, of course, the power-punk duo took off their shirts at the NPR Music offices, because why not? \n\nSet List:\n\n\"Shredder\"\n\"Diamond Way\"\n\"Bummer\"\n\"Bone Jam\"\n\nFor more videos and to subscribe to the Tiny Desk Concerts podcast visit npr.org/tinydeskconcerts.",
    "thumbnails": {
     "default": {
      "url": "https://i.ytimg.com/vi/PsMqTDxboJE/default.jpg",
      "width": 120,
      "height": 90
     },
     "medium": {
      "url": "https://i.ytimg.com/vi/PsMqTDxboJE/mqdefault.jpg",
      "width": 320,
      "height": 180
     },
     "high": {
      "url": "https://i.ytimg.com/vi/PsMqTDxboJE/hqdefault.jpg",
      "width": 480,
      "height": 360
     },
     "standard": {
      "url": "https://i.ytimg.com/vi/PsMqTDxboJE/sddefault.jpg",
      "width": 640,
      "height": 480
     },
     "maxres": {
      "url": "https://i.ytimg.com/vi/PsMqTDxboJE/maxresdefault.jpg",
      "width": 1280,
      "height": 720
     }
    },
    "position": 415
   }
  },
  {
   "snippet": {
    "publishedAt": "2011-12-14T18:42:43.000Z",
    "title": "Mates of State: NPR Music Tiny Desk Concert",
    "description": "The modesty of Mates of State's performance both suits and complements a band  whose music is about generosity of spirit, forgiveness of failing, and  the celebration of all things hard-won enough to be worth celebrating.\n\nSet List: \n\"Sway\"\n\"Desire\"\n\"My Only Offer\"\n\nFor more videos and to subscribe to the Tiny Desk Concerts podcast visit npr.org/tinydeskconcerts",
    "thumbnails": {
     "default": {
      "url": "https://i.ytimg.com/vi/3gP3XrKpy1k/default.jpg",
      "width": 120,
      "height": 90
     },
     "medium": {
      "url": "https://i.ytimg.com/vi/3gP3XrKpy1k/mqdefault.jpg",
      "width": 320,
      "height": 180
     },
     "high": {
      "url": "https://i.ytimg.com/vi/3gP3XrKpy1k/hqdefault.jpg",
      "width": 480,
      "height": 360
     },
     "standard": {
      "url": "https://i.ytimg.com/vi/3gP3XrKpy1k/sddefault.jpg",
      "width": 640,
      "height": 480
     },
     "maxres": {
      "url": "https://i.ytimg.com/vi/3gP3XrKpy1k/maxresdefault.jpg",
      "width": 1280,
      "height": 720
     }
    },
    "position": 416
   }
  },
  {
   "snippet": {
    "publishedAt": "2011-12-12T15:50:33.000Z",
    "title": "tUne-yArDs: NPR Music Tiny Desk Concert",
    "description": "With loop pedals and an irrepressible voice, tUnE-yArDs' Merrill Garbus makes powerful and danceable songs that spring to life before your eyes. Watch Garbus perform three buoyant songs from this year's stunning w h o k i l l.\n\nSet List:\n\n\"You Yes You\"\n\"Doorstep\"\n\"My Country\"\n\nFor more videos and to subscribe to the Tiny Desk Concerts podcast, visit npr.org/tinydeskconcerts.",
    "thumbnails": {
     "default": {
      "url": "https://i.ytimg.com/vi/c8FML8QhcZo/default.jpg",
      "width": 120,
      "height": 90
     },
     "medium": {
      "url": "https://i.ytimg.com/vi/c8FML8QhcZo/mqdefault.jpg",
      "width": 320,
      "height": 180
     },
     "high": {
      "url": "https://i.ytimg.com/vi/c8FML8QhcZo/hqdefault.jpg",
      "width": 480,
      "height": 360
     },
     "standard": {
      "url": "https://i.ytimg.com/vi/c8FML8QhcZo/sddefault.jpg",
      "width": 640,
      "height": 480
     },
     "maxres": {
      "url": "https://i.ytimg.com/vi/c8FML8QhcZo/maxresdefault.jpg",
      "width": 1280,
      "height": 720
     }
    },
    "position": 417
   }
  },
  {
   "snippet": {
    "publishedAt": "2011-12-12T15:22:05.000Z",
    "title": "Private video",
    "description": "This video is private.",
    "position": 418
   }
  },
  {
   "snippet": {
    "publishedAt": "2011-11-30T15:37:10.000Z",
    "title": "Hospital Ships: NPR Music Tiny Desk Concert",
    "description": "On Lonely Twin, Hospital Ships' poppy folk songs and brash rockers are packed with instrumental flourishes and bursts of feedback. But in this stripped-down performance at the NPR Music offices, Jordan Geiger's beautifully crushing songs pack an emotional punch.\n\nSet List:\n\"Phantom Limb\"\n\"Carry On\"\n\"Let Me In\"\n\nFor more videos and to subscribe to the Tiny Desk Concerts podcast, visit npr.org/tinydeskconcerts.",
    "thumbnails": {
     "default": {
      "url": "https://i.ytimg.com/vi/Z3LKrXt7570/default.jpg",
      "width": 120,
      "height": 90
     },
     "medium": {
      "url": "https://i.ytimg.com/vi/Z3LKrXt7570/mqdefault.jpg",
      "width": 320,
      "height": 180
     },
     "high": {
      "url": "https://i.ytimg.com/vi/Z3LKrXt7570/hqdefault.jpg",
      "width": 480,
      "height": 360
     },
     "standard": {
      "url": "https://i.ytimg.com/vi/Z3LKrXt7570/sddefault.jpg",
      "width": 640,
      "height": 480
     },
     "maxres": {
      "url": "https://i.ytimg.com/vi/Z3LKrXt7570/maxresdefault.jpg",
      "width": 1280,
      "height": 720
     }
    },
    "position": 419
   }
  },
  {
   "snippet": {
    "publishedAt": "2011-11-30T15:22:30.000Z",
    "title": "Joe Henry: NPR Music Tiny Desk Concert",
    "description": "Joe Henry's latest record 'Reverie' reflects his fearlessly easygoing style, so asking him to sing in a crowded office never felt like an imposition.\n\nSet List:\n\"Sticks And Stones\"\n\"After The War\"\n\"Odetta\"\n\"Piano Furnace\"\n\nFor more videos and to subscribe to the Tiny Desk Concerts podcast, visit npr.org/tinydeskconcerts.",
    "thumbnails": {
     "default": {
      "url": "https://i.ytimg.com/vi/MA--dI19Lfc/default.jpg",
      "width": 120,
      "height": 90
     },
     "medium": {
      "url": "https://i.ytimg.com/vi/MA--dI19Lfc/mqdefault.jpg",
      "width": 320,
      "height": 180
     },
     "high": {
      "url": "https://i.ytimg.com/vi/MA--dI19Lfc/hqdefault.jpg",
      "width": 480,
      "height": 360
     },
     "standard": {
      "url": "https://i.ytimg.com/vi/MA--dI19Lfc/sddefault.jpg",
      "width": 640,
      "height": 480
     },
     "maxres": {
      "url": "https://i.ytimg.com/vi/MA--dI19Lfc/maxresdefault.jpg",
      "width": 1280,
      "height": 720
     }
    },
    "position": 420
   }
  },
  {
   "snippet": {
    "publishedAt": "2011-11-29T16:42:33.000Z",
    "title": "Yo-Yo Ma, Edgar Meyer, Chris Thile And Stuart Duncan: NPR Music Tiny Desk Concert",
    "description": "The genre-bending cellist Yo-Yo Ma heads a dream team of string players -- Edgar Meyer, Chris Thile, Stuart Duncan -- who borrow from bluegrass. The quartet, plus singer Aoife O'Donovan perform three songs from their album The Goat Rodeo Sessions at the NPR Music offices.\n\nSet List:\n\n\"Quarter Chicken Dark\"\n\"Attaboy\"\n\"Here And Heaven\"\n\nFor more videos and to subscribe to the Tiny Desk Concerts podcast, visit NPR.org/tinydeskconcerts.",
    "thumbnails": {
     "default": {
      "url": "https://i.ytimg.com/vi/O7EcT5YzKhQ/default.jpg",
      "width": 120,
      "height": 90
     },
     "medium": {
      "url": "https://i.ytimg.com/vi/O7EcT5YzKhQ/mqdefault.jpg",
      "width": 320,
      "height": 180
     },
     "high": {
      "url": "https://i.ytimg.com/vi/O7EcT5YzKhQ/hqdefault.jpg",
      "width": 480,
      "height": 360
     },
     "standard": {
      "url": "https://i.ytimg.com/vi/O7EcT5YzKhQ/sddefault.jpg",
      "width": 640,
      "height": 480
     },
     "maxres": {
      "url": "https://i.ytimg.com/vi/O7EcT5YzKhQ/maxresdefault.jpg",
      "width": 1280,
      "height": 720
     }
    },
    "position": 421
   }
  },
  {
   "snippet": {
    "publishedAt": "2011-11-28T05:34:28.000Z",
    "title": "Marketa Irglova: NPR Music Tiny Desk Concert",
    "description": "With the help of Iranian singer-percussionist Aida Shahghasemi, Marketa Irglova crafts a lovely mix of the exotic and the familiar; of sweetness and longing. Watch the pair perform three songs in the NPR Music offices.\n\nSet List:\n\"We Are Good\"\n\"Dokhtar Goochani\"\n\"Let Me Fall In Love\"\n\nFor more videos and to subscribe to the Tiny Desk Concerts podcast, visit npr.org/tinydeskconcerts.",
    "thumbnails": {
     "default": {
      "url": "https://i.ytimg.com/vi/4cwIj0tzPr4/default.jpg",
      "width": 120,
      "height": 90
     },
     "medium": {
      "url": "https://i.ytimg.com/vi/4cwIj0tzPr4/mqdefault.jpg",
      "width": 320,
      "height": 180
     },
     "high": {
      "url": "https://i.ytimg.com/vi/4cwIj0tzPr4/hqdefault.jpg",
      "width": 480,
      "height": 360
     },
     "standard": {
      "url": "https://i.ytimg.com/vi/4cwIj0tzPr4/sddefault.jpg",
      "width": 640,
      "height": 480
     },
     "maxres": {
      "url": "https://i.ytimg.com/vi/4cwIj0tzPr4/maxresdefault.jpg",
      "width": 1280,
      "height": 720
     }
    },
    "position": 422
   }
  },
  {
   "snippet": {
    "publishedAt": "2011-11-07T16:14:15.000Z",
    "title": "Jens Lekman: NPR Music Tiny Desk Concert",
    "description": "Jens Lekman is a singer-songwriter, storyteller, actor and comedian whose banter falls somewhere between the effortless delivery of a seasoned comic and the nervous rambling of an indie-rock frontman. Lekman shows off his humor and charm in this intimate set at the NPR Music offices.\r\n\r\nSet List:\r\n\"I Want A Pair Of Cowboy Boots\"\r\n\"The End Of The World Is Bigger Than Love\"\r\n\"Waiting For Kirsten\"\r\n\r\nFor more videos and to subscribe to the Tiny Desk Concerts podcast, visit npr.org/tinydeskconcerts.",
    "thumbnails": {
     "default": {
      "url": "https://i.ytimg.com/vi/wftQvpqo6Rg/default.jpg",
      "width": 120,
      "height": 90
     },
     "medium": {
      "url": "https://i.ytimg.com/vi/wftQvpqo6Rg/mqdefault.jpg",
      "width": 320,
      "height": 180
     },
     "high": {
      "url": "https://i.ytimg.com/vi/wftQvpqo6Rg/hqdefault.jpg",
      "width": 480,
      "height": 360
     },
     "standard": {
      "url": "https://i.ytimg.com/vi/wftQvpqo6Rg/sddefault.jpg",
      "width": 640,
      "height": 480
     },
     "maxres": {
      "url": "https://i.ytimg.com/vi/wftQvpqo6Rg/maxresdefault.jpg",
      "width": 1280,
      "height": 720
     }
    },
    "position": 423
   }
  },
  {
   "snippet": {
    "publishedAt": "2011-11-03T14:27:38.000Z",
    "title": "Juanes: NPR Music Tiny Desk Concert",
    "description": "Juanes' five albums have struck a chord with millions, making him a superstar who can fill stadiums and large arenas across Latin America and the U.S. Watch the charismatic Colombian superstar give an intimate performance at the NPR Music offices.\n\nSet List:\n\"Hoy Me Voy\"\n\"Yerbatero\"\n\"La Camisa Negra\"\n\nFor more videos and to subscribe to the Tiny Desk Concerts, visit npr.org/tinydeskconcerts.",
    "thumbnails": {
     "default": {
      "url": "https://i.ytimg.com/vi/TG6NqII3Zuw/default.jpg",
      "width": 120,
      "height": 90
     },
     "medium": {
      "url": "https://i.ytimg.com/vi/TG6NqII3Zuw/mqdefault.jpg",
      "width": 320,
      "height": 180
     },
     "high": {
      "url": "https://i.ytimg.com/vi/TG6NqII3Zuw/hqdefault.jpg",
      "width": 480,
      "height": 360
     },
     "standard": {
      "url": "https://i.ytimg.com/vi/TG6NqII3Zuw/sddefault.jpg",
      "width": 640,
      "height": 480
     },
     "maxres": {
      "url": "https://i.ytimg.com/vi/TG6NqII3Zuw/maxresdefault.jpg",
      "width": 1280,
      "height": 720
     }
    },
    "position": 424
   }
  },
  {
   "snippet": {
    "publishedAt": "2011-10-31T22:03:38.000Z",
    "title": "Lisa Hannigan: NPR Music Tiny Desk Concert",
    "description": "Exuding both musical and personal warmth, the Irish singer mesmerized at the NPR Music offices.\n\nSet List: \n\"Knots\"\n\"Little Bird\"\n\"Passenger\"\n\nFor more videos and to subscribe to the Tiny Desk Concerts podcast, visit npr.org/tinydeskconcerts.",
    "thumbnails": {
     "default": {
      "url": "https://i.ytimg.com/vi/r-B_fkZfWjk/default.jpg",
      "width": 120,
      "height": 90
     },
     "medium": {
      "url": "https://i.ytimg.com/vi/r-B_fkZfWjk/mqdefault.jpg",
      "width": 320,
      "height": 180
     },
     "high": {
      "url": "https://i.ytimg.com/vi/r-B_fkZfWjk/hqdefault.jpg",
      "width": 480,
      "height": 360
     },
     "standard": {
      "url": "https://i.ytimg.com/vi/r-B_fkZfWjk/sddefault.jpg",
      "width": 640,
      "height": 480
     },
     "maxres": {
      "url": "https://i.ytimg.com/vi/r-B_fkZfWjk/maxresdefault.jpg",
      "width": 1280,
      "height": 720
     }
    },
    "position": 425
   }
  },
  {
   "snippet": {
    "publishedAt": "2011-10-24T14:33:52.000Z",
    "title": "Ben Williams, NPR Tiny Desk Concert",
    "description": "Bassist Ben Williams is a rising jazz star. He won the 2009 Thelonious Monk Competition and received a recording contract for his debut album, State of Art, which was released this summer. Williams brought his band Sound Effect to perform two songs from that album at the NPR Music offices.\r\n\r\nSet List: \r\n\"Home\"\r\n\"Dawn Of A New Day\"\r\n\r\nFor more videos and to subscribe to the Tiny Desk Concerts podcast, visit npr.org/tinydeskconcerts.",
    "thumbnails": {
     "default": {
      "url": "https://i.ytimg.com/vi/rsMLQVRS3ho/default.jpg",
      "width": 120,
      "height": 90
     },
     "medium": {
      "url": "https://i.ytimg.com/vi/rsMLQVRS3ho/mqdefault.jpg",
      "width": 320,
      "height": 180
     },
     "high": {
      "url": "https://i.ytimg.com/vi/rsMLQVRS3ho/hqdefault.jpg",
      "width": 480,
      "height": 360
     },
     "standard": {
      "url": "https://i.ytimg.com/vi/rsMLQVRS3ho/sddefault.jpg",
      "width": 640,
      "height": 480
     },
     "maxres": {
      "url": "https://i.ytimg.com/vi/rsMLQVRS3ho/maxresdefault.jpg",
      "width": 1280,
      "height": 720
     }
    },
    "position": 426
   }
  },
  {
   "snippet": {
    "publishedAt": "2011-10-24T14:19:32.000Z",
    "title": "Hilary Hahn: NPR Music Tiny Desk Concert",
    "description": "The classical violinist blends Bach and Charles Ives with flair, then tops it off with a fedora.\n\nSet List:\nBach: Bouree (from Partita No. 3)\nBach: Siciliana (from Sonata No. 1)\nIves/Trad.: Medley\n\nFor more videos and to subscribe to the Tiny Desk Concerts podcast, visit npr.org/tinydeskconcerts.",
    "thumbnails": {
     "default": {
      "url": "https://i.ytimg.com/vi/cBNTDlI1-nQ/default.jpg",
      "width": 120,
      "height": 90
     },
     "medium": {
      "url": "https://i.ytimg.com/vi/cBNTDlI1-nQ/mqdefault.jpg",
      "width": 320,
      "height": 180
     },
     "high": {
      "url": "https://i.ytimg.com/vi/cBNTDlI1-nQ/hqdefault.jpg",
      "width": 480,
      "height": 360
     },
     "standard": {
      "url": "https://i.ytimg.com/vi/cBNTDlI1-nQ/sddefault.jpg",
      "width": 640,
      "height": 480
     },
     "maxres": {
      "url": "https://i.ytimg.com/vi/cBNTDlI1-nQ/maxresdefault.jpg",
      "width": 1280,
      "height": 720
     }
    },
    "position": 427
   }
  },
  {
   "snippet": {
    "publishedAt": "2011-10-18T15:38:45.000Z",
    "title": "Wilco: NPR Music Tiny Desk Concert",
    "description": "Armed with acoustic guitars, tiny amps, a desktop percussion unit and a ton of grace, Wilco plays three new songs from The Whole Love and an old favorite in a stripped-down but powerful set at the NPR Music offices.\n\nSet List:\n\"Dawned On Me\"\n\"Whole Love\"\n\"Born Alone\"\n\"War On War\"\n\nFor more videos and to subscribe to the Tiny Desk Concerts podcast, visit npr.org/tinydeskconcerts.",
    "thumbnails": {
     "default": {
      "url": "https://i.ytimg.com/vi/UZAKTCeE70Y/default.jpg",
      "width": 120,
      "height": 90
     },
     "medium": {
      "url": "https://i.ytimg.com/vi/UZAKTCeE70Y/mqdefault.jpg",
      "width": 320,
      "height": 180
     },
     "high": {
      "url": "https://i.ytimg.com/vi/UZAKTCeE70Y/hqdefault.jpg",
      "width": 480,
      "height": 360
     },
     "standard": {
      "url": "https://i.ytimg.com/vi/UZAKTCeE70Y/sddefault.jpg",
      "width": 640,
      "height": 480
     },
     "maxres": {
      "url": "https://i.ytimg.com/vi/UZAKTCeE70Y/maxresdefault.jpg",
      "width": 1280,
      "height": 720
     }
    },
    "position": 428
   }
  },
  {
   "snippet": {
    "publishedAt": "2011-10-18T15:15:18.000Z",
    "title": "Chris Bathgate: NPR Music Tiny Desk Concert",
    "description": "Dusky and deliberate, Chris Bathgate's music can be foreboding, even funereal. But the Michigan native invests his songs with warm, rustic beauty, which makes everything too pretty to function as a true downer.\n\nSet List:\n\"Everything (Overture)\"\n\"No Silver\"\n\"Salt Year\"\n\"Levee\"\n\nFor more videos and to subscribe to the Tiny Desk Concerts podcast, visit npr.org/tinydeskconcerts.",
    "thumbnails": {
     "default": {
      "url": "https://i.ytimg.com/vi/WRJXePSFApU/default.jpg",
      "width": 120,
      "height": 90
     },
     "medium": {
      "url": "https://i.ytimg.com/vi/WRJXePSFApU/mqdefault.jpg",
      "width": 320,
      "height": 180
     },
     "high": {
      "url": "https://i.ytimg.com/vi/WRJXePSFApU/hqdefault.jpg",
      "width": 480,
      "height": 360
     },
     "standard": {
      "url": "https://i.ytimg.com/vi/WRJXePSFApU/sddefault.jpg",
      "width": 640,
      "height": 480
     },
     "maxres": {
      "url": "https://i.ytimg.com/vi/WRJXePSFApU/maxresdefault.jpg",
      "width": 1280,
      "height": 720
     }
    },
    "position": 429
   }
  },
  {
   "snippet": {
    "publishedAt": "2011-10-06T16:29:49.000Z",
    "title": "Fountains Of Wayne: NPR Music Tiny Desk Concert",
    "description": "It speaks well of this performance that Fountains of Wayne's set pokes around in a few gray areas; its four songs showcase a band with tremendous narrative gifts and a real flair for subtle beauty.\n\nSet List:\n\"The Summer Place\"\n\"Valley Winter Song\"\n\"A Dip In The Ocean\"\n\"Troubled Times\"\n\nFor more videos and to subscribe to the Tiny Desk Concerts podcast, visit npr.org/tinydeskconcerts.",
    "thumbnails": {
     "default": {
      "url": "https://i.ytimg.com/vi/nIO1tXMnt4E/default.jpg",
      "width": 120,
      "height": 90
     },
     "medium": {
      "url": "https://i.ytimg.com/vi/nIO1tXMnt4E/mqdefault.jpg",
      "width": 320,
      "height": 180
     },
     "high": {
      "url": "https://i.ytimg.com/vi/nIO1tXMnt4E/hqdefault.jpg",
      "width": 480,
      "height": 360
     },
     "standard": {
      "url": "https://i.ytimg.com/vi/nIO1tXMnt4E/sddefault.jpg",
      "width": 640,
      "height": 480
     },
     "maxres": {
      "url": "https://i.ytimg.com/vi/nIO1tXMnt4E/maxresdefault.jpg",
      "width": 1280,
      "height": 720
     }
    },
    "position": 430
   }
  },
  {
   "snippet": {
    "publishedAt": "2011-10-03T15:35:42.000Z",
    "title": "Trombone Shorty: NPR Music Tiny Desk Concert",
    "description": "He can play the horn. He can sing. And that's made him the latest musical star of a great New Orleans tradition. But Trombone Shorty mainly just wants you to dance: \"I know you came here to move,\" he sings to an office full of NPR staff. \n\nSet List:\n\"Dumaine St.\"\n\"Lagniappe\"\n\"Do To Me\"\n\nFor more videos and to subscribe to the Tiny Desk Concerts podcast, visit npr.org/tinydeskconcerts.",
    "thumbnails": {
     "default": {
      "url": "https://i.ytimg.com/vi/cwYAeUpH1NM/default.jpg",
      "width": 120,
      "height": 90
     },
     "medium": {
      "url": "https://i.ytimg.com/vi/cwYAeUpH1NM/mqdefault.jpg",
      "width": 320,
      "height": 180
     },
     "high": {
      "url": "https://i.ytimg.com/vi/cwYAeUpH1NM/hqdefault.jpg",
      "width": 480,
      "height": 360
     },
     "standard": {
      "url": "https://i.ytimg.com/vi/cwYAeUpH1NM/sddefault.jpg",
      "width": 640,
      "height": 480
     },
     "maxres": {
      "url": "https://i.ytimg.com/vi/cwYAeUpH1NM/maxresdefault.jpg",
      "width": 1280,
      "height": 720
     }
    },
    "position": 431
   }
  },
  {
   "snippet": {
    "publishedAt": "2011-10-03T15:15:28.000Z",
    "title": "The Klezmatics: NPR Music Tiny Desk Concert",
    "description": "Ring in Rosh Hashanah with three globe-trotting tunes from one of the world's greatest Jewish bands.\n\nSet List:\n\"Gilad and Ziv's Sirba\" (Lorin Sklamberg)\n\"Holy Ground\" (Frank London; lyrics by Woody Guthrie)\n\"Zol shoyn kumen di geule\" (Shmerke Kaczerginsky; arranged by Frank London)\n\nFor more videos and to subscribe to the Tiny Desk Concerts podcast, visit npr.org/tinydeskconcerts.",
    "thumbnails": {
     "default": {
      "url": "https://i.ytimg.com/vi/w4AC_-MoqMM/default.jpg",
      "width": 120,
      "height": 90
     },
     "medium": {
      "url": "https://i.ytimg.com/vi/w4AC_-MoqMM/mqdefault.jpg",
      "width": 320,
      "height": 180
     },
     "high": {
      "url": "https://i.ytimg.com/vi/w4AC_-MoqMM/hqdefault.jpg",
      "width": 480,
      "height": 360
     },
     "standard": {
      "url": "https://i.ytimg.com/vi/w4AC_-MoqMM/sddefault.jpg",
      "width": 640,
      "height": 480
     },
     "maxres": {
      "url": "https://i.ytimg.com/vi/w4AC_-MoqMM/maxresdefault.jpg",
      "width": 1280,
      "height": 720
     }
    },
    "position": 432
   }
  },
  {
   "snippet": {
    "publishedAt": "2011-10-03T15:02:58.000Z",
    "title": "Jenny Lin: NPR Music Tiny Desk Concert",
    "description": "The eminent pianist usually plays eight-foot Steinways. See what she does on an electronic keyboard in this intimate performance at the NPR Music offices. \n\nSet List:\n-- Dmitri Shostakovich: Prelude and Fugue No. 2 in A minor, Op. 87\n-- Dmitri Shostakovich: Prelude and Fugue No. 7 in A major, Op. 87\n-- Federico Mompou: Musica Callada — Nos. 1, 15\n-- Gershwin (arr. Earl Wild): \"Fascinatin' Rhythm\"\n\nFor more videos and to subscribe to the Tiny Desk Concerts podcast, visit npr.org/tinydeskconcerts.",
    "thumbnails": {
     "default": {
      "url": "https://i.ytimg.com/vi/p1i28p_gyFI/default.jpg",
      "width": 120,
      "height": 90
     },
     "medium": {
      "url": "https://i.ytimg.com/vi/p1i28p_gyFI/mqdefault.jpg",
      "width": 320,
      "height": 180
     },
     "high": {
      "url": "https://i.ytimg.com/vi/p1i28p_gyFI/hqdefault.jpg",
      "width": 480,
      "height": 360
     },
     "standard": {
      "url": "https://i.ytimg.com/vi/p1i28p_gyFI/sddefault.jpg",
      "width": 640,
      "height": 480
     },
     "maxres": {
      "url": "https://i.ytimg.com/vi/p1i28p_gyFI/maxresdefault.jpg",
      "width": 1280,
      "height": 720
     }
    },
    "position": 433
   }
  },
  {
   "snippet": {
    "publishedAt": "2011-09-22T03:52:17.000Z",
    "title": "Beirut: NPR Music Tiny Desk Concert",
    "description": "Beirut arrived at the NPR Music offices dusty and exhausted following a weekend at Bonnaroo in Tennessee. But after some much-needed showers, the band brought infectious joy to its short set behind the Tiny Desk.\n\nSet List:\n\"East Harlem\"\n\"Sante Fe\"\n\"Serbian Cocek\"\n\nFor more videos and to subscribe to the Tiny Desk Concerts podcast, visit npr.org/tinydeskconcerts.",
    "thumbnails": {
     "default": {
      "url": "https://i.ytimg.com/vi/Z0UISCEe52Y/default.jpg",
      "width": 120,
      "height": 90
     },
     "medium": {
      "url": "https://i.ytimg.com/vi/Z0UISCEe52Y/mqdefault.jpg",
      "width": 320,
      "height": 180
     },
     "high": {
      "url": "https://i.ytimg.com/vi/Z0UISCEe52Y/hqdefault.jpg",
      "width": 480,
      "height": 360
     },
     "standard": {
      "url": "https://i.ytimg.com/vi/Z0UISCEe52Y/sddefault.jpg",
      "width": 640,
      "height": 480
     },
     "maxres": {
      "url": "https://i.ytimg.com/vi/Z0UISCEe52Y/maxresdefault.jpg",
      "width": 1280,
      "height": 720
     }
    },
    "position": 434
   }
  },
  {
   "snippet": {
    "publishedAt": "2011-09-19T19:22:31.000Z",
    "title": "Jeremy Messersmith: NPR Music Tiny Desk Concert",
    "description": "With his horn-rimmed glasses and esoteric subject matter, Messersmith is no rock star. But he's a pop genius, with creative  ambition to match his songs' considerable charm.\n\nSet List:\n\"Toussaint Grey, First In Life And Death\"\n\"Knots\"\n\"Violet\"\n\"A Girl, A Boy, And A Graveyard\"\n\"Tatooine\"\n\nFor more videos and to subscribe to the Tiny Desk Concerts podcast, visit npr.org/tinydeskconcerts.",
    "thumbnails": {
     "default": {
      "url": "https://i.ytimg.com/vi/X-RVUGjCfug/default.jpg",
      "width": 120,
      "height": 90
     },
     "medium": {
      "url": "https://i.ytimg.com/vi/X-RVUGjCfug/mqdefault.jpg",
      "width": 320,
      "height": 180
     },
     "high": {
      "url": "https://i.ytimg.com/vi/X-RVUGjCfug/hqdefault.jpg",
      "width": 480,
      "height": 360
     },
     "standard": {
      "url": "https://i.ytimg.com/vi/X-RVUGjCfug/sddefault.jpg",
      "width": 640,
      "height": 480
     },
     "maxres": {
      "url": "https://i.ytimg.com/vi/X-RVUGjCfug/maxresdefault.jpg",
      "width": 1280,
      "height": 720
     }
    },
    "position": 435
   }
  },
  {
   "snippet": {
    "publishedAt": "2011-09-19T17:22:22.000Z",
    "title": "Sean Rowe: NPR Music Tiny Desk Concert",
    "description": "The singer-songwriter brings his booming voice and a succession of ever-louder acoustic-guitar set-ups to the NPR Music offices. And, for good measure, he tells a story about survivalism that'll renew your faith in indoor living.\n\nSet List:\n\"Night\"\n\"Bluegrass Baby\"\n\"Surprise\"\n\nFor more videos and to subscribe to the Tiny Desk Concerts podcast, visit npr.org/tinydeskconcerts.",
    "thumbnails": {
     "default": {
      "url": "https://i.ytimg.com/vi/mTkmIgrj1CA/default.jpg",
      "width": 120,
      "height": 90
     },
     "medium": {
      "url": "https://i.ytimg.com/vi/mTkmIgrj1CA/mqdefault.jpg",
      "width": 320,
      "height": 180
     },
     "high": {
      "url": "https://i.ytimg.com/vi/mTkmIgrj1CA/hqdefault.jpg",
      "width": 480,
      "height": 360
     },
     "standard": {
      "url": "https://i.ytimg.com/vi/mTkmIgrj1CA/sddefault.jpg",
      "width": 640,
      "height": 480
     },
     "maxres": {
      "url": "https://i.ytimg.com/vi/mTkmIgrj1CA/maxresdefault.jpg",
      "width": 1280,
      "height": 720
     }
    },
    "position": 436
   }
  },
  {
   "snippet": {
    "publishedAt": "2011-09-19T16:20:56.000Z",
    "title": "Diego Garcia: NPR Music Tiny Desk Concert",
    "description": "Taken individually, each tune on Diego Garcia's album 'Laura' is lovely. But listen to each  song in sequence and it's even better, like a good book: The  sum is greater than the parts. Watch Garcia perform songs from 'Laura' at the NPR Music offices.\n\nSet List:\n\"Nothing To Hide\"\n\"You Were Never There\"\n\"Under This Spell\"\n\"Stay\"\n\nFor more videos and to subscribe to the Tiny Desk Concerts podcast, visit npr.org/tinydeskconcerts.",
    "thumbnails": {
     "default": {
      "url": "https://i.ytimg.com/vi/DjmHpDI89v8/default.jpg",
      "width": 120,
      "height": 90
     },
     "medium": {
      "url": "https://i.ytimg.com/vi/DjmHpDI89v8/mqdefault.jpg",
      "width": 320,
      "height": 180
     },
     "high": {
      "url": "https://i.ytimg.com/vi/DjmHpDI89v8/hqdefault.jpg",
      "width": 480,
      "height": 360
     },
     "standard": {
      "url": "https://i.ytimg.com/vi/DjmHpDI89v8/sddefault.jpg",
      "width": 640,
      "height": 480
     },
     "maxres": {
      "url": "https://i.ytimg.com/vi/DjmHpDI89v8/maxresdefault.jpg",
      "width": 1280,
      "height": 720
     }
    },
    "position": 437
   }
  },
  {
   "snippet": {
    "publishedAt": "2011-09-13T03:25:16.000Z",
    "title": "Foster The People: NPR Music Tiny Desk Concert",
    "description": "Armed with the summer song of 2011, the band brings \"Pumped Up Kicks\" and more to NPR Music.\n\nSet List:\n\"Houdini\"\n\"Helena Beat\"\n\"Pumped Up Kicks\"\n\nFor more videos and to subscribe to the Tiny Desk Concerts podcast, visit npr.org/tinydeskconcerts.",
    "thumbnails": {
     "default": {
      "url": "https://i.ytimg.com/vi/kMnDHUKGMWs/default.jpg",
      "width": 120,
      "height": 90
     },
     "medium": {
      "url": "https://i.ytimg.com/vi/kMnDHUKGMWs/mqdefault.jpg",
      "width": 320,
      "height": 180
     },
     "high": {
      "url": "https://i.ytimg.com/vi/kMnDHUKGMWs/hqdefault.jpg",
      "width": 480,
      "height": 360
     },
     "standard": {
      "url": "https://i.ytimg.com/vi/kMnDHUKGMWs/sddefault.jpg",
      "width": 640,
      "height": 480
     },
     "maxres": {
      "url": "https://i.ytimg.com/vi/kMnDHUKGMWs/maxresdefault.jpg",
      "width": 1280,
      "height": 720
     }
    },
    "position": 438
   }
  },
  {
   "snippet": {
    "publishedAt": "2011-09-06T16:26:14.000Z",
    "title": "King Creosote And Jon Hopkins: NPR Music Tiny Desk Concerts",
    "description": "To immerse yourself in King Creosote and Jon Hopkins' album Diamond Mine is to be transported to the Scottish countryside. Standing in the NPR Music offices, the album's unassuming creators somehow lose little of their mystique.\n\nSet List:\n\"John Taylor's Month Away\"\n\"Bubble\"\n\"Cockle Shell\"\n\"And The Racket They Made\"\n\nFor more videos and to subscribe to the Tiny Desk Concerts Podcast, visit npr.org/tinydeskconcerts",
    "thumbnails": {
     "default": {
      "url": "https://i.ytimg.com/vi/ej8vMh28SJY/default.jpg",
      "width": 120,
      "height": 90
     },
     "medium": {
      "url": "https://i.ytimg.com/vi/ej8vMh28SJY/mqdefault.jpg",
      "width": 320,
      "height": 180
     },
     "high": {
      "url": "https://i.ytimg.com/vi/ej8vMh28SJY/hqdefault.jpg",
      "width": 480,
      "height": 360
     },
     "standard": {
      "url": "https://i.ytimg.com/vi/ej8vMh28SJY/sddefault.jpg",
      "width": 640,
      "height": 480
     },
     "maxres": {
      "url": "https://i.ytimg.com/vi/ej8vMh28SJY/maxresdefault.jpg",
      "width": 1280,
      "height": 720
     }
    },
    "position": 439
   }
  },
  {
   "snippet": {
    "publishedAt": "2011-09-01T18:28:41.000Z",
    "title": "Phosphorescent: NPR Music Tiny Desk Concert",
    "description": "Phosphorescent's Matthew Houck specializes in a sort of free-wheeling weariness, with songs and characters that work extremely hard at taking it easy. Watch Houck play a stirring, road-ragged solo Tiny Desk Concert at the NPR Music offices.\n\nSet List:\n\"My Dove, My Lamb\"\n\"We'll Be Here Soon\"\n\"The Mermaid Parade\"\n\"Los Angeles\"\n\nFor more videos or to subscribe to the Tiny Desk Concerts podcast, visit npr.org/tinydeskconcerts",
    "thumbnails": {
     "default": {
      "url": "https://i.ytimg.com/vi/S8m_Oek-Xec/default.jpg",
      "width": 120,
      "height": 90
     },
     "medium": {
      "url": "https://i.ytimg.com/vi/S8m_Oek-Xec/mqdefault.jpg",
      "width": 320,
      "height": 180
     },
     "high": {
      "url": "https://i.ytimg.com/vi/S8m_Oek-Xec/hqdefault.jpg",
      "width": 480,
      "height": 360
     },
     "standard": {
      "url": "https://i.ytimg.com/vi/S8m_Oek-Xec/sddefault.jpg",
      "width": 640,
      "height": 480
     },
     "maxres": {
      "url": "https://i.ytimg.com/vi/S8m_Oek-Xec/maxresdefault.jpg",
      "width": 1280,
      "height": 720
     }
    },
    "position": 440
   }
  },
  {
   "snippet": {
    "publishedAt": "2011-08-29T16:44:07.000Z",
    "title": "CALLmeKAT: NPR Music Tiny Desk Concert",
    "description": "As CALLmeKAT, Katrine Ottosen produces airy, synth-infused pop that pairs melancholy sentiment with sparse melodies. Watch the singer perform a hauntingly beautiful Tiny Desk Concert at the NPR Music offices.\n\nSet List:\n\"Tigerhead\"\n\"Going Home\"\n\"Glass Walls\"\n\nFor more videos and to subscribe to the Tiny Desk Concerts podcast, visit npr.org/tinydeskconcerts",
    "thumbnails": {
     "default": {
      "url": "https://i.ytimg.com/vi/tOXCEV4V8Ks/default.jpg",
      "width": 120,
      "height": 90
     },
     "medium": {
      "url": "https://i.ytimg.com/vi/tOXCEV4V8Ks/mqdefault.jpg",
      "width": 320,
      "height": 180
     },
     "high": {
      "url": "https://i.ytimg.com/vi/tOXCEV4V8Ks/hqdefault.jpg",
      "width": 480,
      "height": 360
     },
     "standard": {
      "url": "https://i.ytimg.com/vi/tOXCEV4V8Ks/sddefault.jpg",
      "width": 640,
      "height": 480
     },
     "maxres": {
      "url": "https://i.ytimg.com/vi/tOXCEV4V8Ks/maxresdefault.jpg",
      "width": 1280,
      "height": 720
     }
    },
    "position": 441
   }
  },
  {
   "snippet": {
    "publishedAt": "2011-08-25T17:00:24.000Z",
    "title": "James Vincent McMorrow: NPR Music Tiny Desk Concert",
    "description": "The Irish songwriter has one of the most arresting voices of any young singer you're likely to hear this year.  See McMorrow give an intimate acoustic performance at the NPR Music offices.\n\nSet List:\n\"This Old Dark Machine\"\n\"Sparrow And The Wolf\"\n\"Follow You Down To The Red Oak Tree\"\n\"Red Dust\"\n\nFor more videos and to subscribe to the Tiny Desk Concerts podcast, visit npr.org/tinydeskconcerts",
    "thumbnails": {
     "default": {
      "url": "https://i.ytimg.com/vi/F-u3SOPjN38/default.jpg",
      "width": 120,
      "height": 90
     },
     "medium": {
      "url": "https://i.ytimg.com/vi/F-u3SOPjN38/mqdefault.jpg",
      "width": 320,
      "height": 180
     },
     "high": {
      "url": "https://i.ytimg.com/vi/F-u3SOPjN38/hqdefault.jpg",
      "width": 480,
      "height": 360
     },
     "standard": {
      "url": "https://i.ytimg.com/vi/F-u3SOPjN38/sddefault.jpg",
      "width": 640,
      "height": 480
     },
     "maxres": {
      "url": "https://i.ytimg.com/vi/F-u3SOPjN38/maxresdefault.jpg",
      "width": 1280,
      "height": 720
     }
    },
    "position": 442
   }
  },
  {
   "snippet": {
    "publishedAt": "2011-08-22T16:13:27.000Z",
    "title": "Other Lives: NPR Music Tiny Desk Concert",
    "description": "The Oklahoma band's droning minor-key hymns were seemingly made for wide-open spaces and big skies. The group brings that spirit to the Tiny Desk for a spacious but intimate performance at the NPR Music offices.\n\nSet List:\n\"For 12\"\n\"Old Statues\"\n\"Dust Bowl III\"\n\nFor more videos and to subscribe to the Tiny Desk Concerts podcast, visit npr.org/tinydeskconcerts",
    "thumbnails": {
     "default": {
      "url": "https://i.ytimg.com/vi/zdX9TmoUid4/default.jpg",
      "width": 120,
      "height": 90
     },
     "medium": {
      "url": "https://i.ytimg.com/vi/zdX9TmoUid4/mqdefault.jpg",
      "width": 320,
      "height": 180
     },
     "high": {
      "url": "https://i.ytimg.com/vi/zdX9TmoUid4/hqdefault.jpg",
      "width": 480,
      "height": 360
     },
     "standard": {
      "url": "https://i.ytimg.com/vi/zdX9TmoUid4/sddefault.jpg",
      "width": 640,
      "height": 480
     },
     "maxres": {
      "url": "https://i.ytimg.com/vi/zdX9TmoUid4/maxresdefault.jpg",
      "width": 1280,
      "height": 720
     }
    },
    "position": 443
   }
  },
  {
   "snippet": {
    "publishedAt": "2011-08-22T15:24:36.000Z",
    "title": "Gaby Moreno: NPR Music Tiny Desk Concert",
    "description": "Moreno's breathtaking voice is passionate and stylistically malleable, as she glides back and forth easily between bossa nova and bluesy rock. Moreno sings three songs from her newest album, Illustrated Songs, at the NPR Music offices.\n\nSet List:\n\"No Regrets\"\n\"Ave Que Emigra\"\n\"Sing Me Life\"\n\nFor more videos and to subscribe to the Tiny Desk Concerts podcast, visit npr.org/tinydeskconcerts",
    "thumbnails": {
     "default": {
      "url": "https://i.ytimg.com/vi/sIdRsY5HJGw/default.jpg",
      "width": 120,
      "height": 90
     },
     "medium": {
      "url": "https://i.ytimg.com/vi/sIdRsY5HJGw/mqdefault.jpg",
      "width": 320,
      "height": 180
     },
     "high": {
      "url": "https://i.ytimg.com/vi/sIdRsY5HJGw/hqdefault.jpg",
      "width": 480,
      "height": 360
     },
     "standard": {
      "url": "https://i.ytimg.com/vi/sIdRsY5HJGw/sddefault.jpg",
      "width": 640,
      "height": 480
     },
     "maxres": {
      "url": "https://i.ytimg.com/vi/sIdRsY5HJGw/maxresdefault.jpg",
      "width": 1280,
      "height": 720
     }
    },
    "position": 444
   }
  },
  {
   "snippet": {
    "publishedAt": "2011-08-15T19:13:56.000Z",
    "title": "Paul Jacobs: NPR Music Tiny Desk Concert",
    "description": "The Grammy-winning organist showcases his miraculous hands (and feet) in an all-Bach performance.\n\nSet List:\n\n\n\n\nJ.S. Bach: \"Gigue\" Fugue\nJ.S. Bach: Arioso\nBach/Reger: Invention in F Major\nJ.S. Bach: Fugue in A Minor\n\nFor more videos and to subscribe to the Tiny Desk Concerts podcast, visit npr.org/tinydeskconcerts",
    "thumbnails": {
     "default": {
      "url": "https://i.ytimg.com/vi/TlW29RhUkDc/default.jpg",
      "width": 120,
      "height": 90
     },
     "medium": {
      "url": "https://i.ytimg.com/vi/TlW29RhUkDc/mqdefault.jpg",
      "width": 320,
      "height": 180
     },
     "high": {
      "url": "https://i.ytimg.com/vi/TlW29RhUkDc/hqdefault.jpg",
      "width": 480,
      "height": 360
     },
     "standard": {
      "url": "https://i.ytimg.com/vi/TlW29RhUkDc/sddefault.jpg",
      "width": 640,
      "height": 480
     },
     "maxres": {
      "url": "https://i.ytimg.com/vi/TlW29RhUkDc/maxresdefault.jpg",
      "width": 1280,
      "height": 720
     }
    },
    "position": 445
   }
  },
  {
   "snippet": {
    "publishedAt": "2011-08-10T14:37:16.000Z",
    "title": "Noah And The Whale: NPR Music Tiny Desk Concert",
    "description": "A few years ago, Noah and the Whale would have seemed like the last band to bring a drum machine to a Tiny Desk Concert. But here, the London band plugs in -- and sweet simplicity still reigns.\n\nSet List:\n\n\"L.I.F.E.G.O.E.S.O.N.\"\n\"Blue Skies\"\n\"Waiting For My Chance To Come\"\n\nFor more videos and to subscribe to the Tiny Desk Concerts Podcast, visit npr.org/tinydeskconcerts",
    "thumbnails": {
     "default": {
      "url": "https://i.ytimg.com/vi/efiBs11W1Ps/default.jpg",
      "width": 120,
      "height": 90
     },
     "medium": {
      "url": "https://i.ytimg.com/vi/efiBs11W1Ps/mqdefault.jpg",
      "width": 320,
      "height": 180
     },
     "high": {
      "url": "https://i.ytimg.com/vi/efiBs11W1Ps/hqdefault.jpg",
      "width": 480,
      "height": 360
     },
     "standard": {
      "url": "https://i.ytimg.com/vi/efiBs11W1Ps/sddefault.jpg",
      "width": 640,
      "height": 480
     },
     "maxres": {
      "url": "https://i.ytimg.com/vi/efiBs11W1Ps/maxresdefault.jpg",
      "width": 1280,
      "height": 720
     }
    },
    "position": 446
   }
  },
  {
   "snippet": {
    "publishedAt": "2015-05-04T14:13:01.000Z",
    "title": "Rodrigo y Gabriela: NPR Music Tiny Desk Concert",
    "description": "I can't think of a better way to describe the music of Rodrigo y Gabriela than with three words: \"heavy metal flamenco.\" And yet the duo doesn't play heavy metal — its members perform instrumentals on nylon-string guitars — nor does it play Spanish dance music. But the term fits because the pair's fierce guitar riffs feel powerfully electric, and because Rodrigo y Gabriela's rhythmic style showcases a frenetic strum that conjures the energy of flamenco.\r\n\r\nThe duo have just released a new album titled, 11:11, which pays tribute to the pair's heroes — Jimi Hendrix, Carlos Santana, Astor Piazzolla and Pantera's Dimebag Darrell. They recently performed a few tracks for the NPR Music Tiny Desk series including \"Hanuman\" and \"Buster Voodoo.\"",
    "thumbnails": {
     "default": {
      "url": "https://i.ytimg.com/vi/wKd0HNg1kFQ/default.jpg",
      "width": 120,
      "height": 90
     },
     "medium": {
      "url": "https://i.ytimg.com/vi/wKd0HNg1kFQ/mqdefault.jpg",
      "width": 320,
      "height": 180
     },
     "high": {
      "url": "https://i.ytimg.com/vi/wKd0HNg1kFQ/hqdefault.jpg",
      "width": 480,
      "height": 360
     },
     "standard": {
      "url": "https://i.ytimg.com/vi/wKd0HNg1kFQ/sddefault.jpg",
      "width": 640,
      "height": 480
     }
    },
    "position": 447
   }
  }
 ]
}
